LuanSpaceship/AddColorsAndStyles.py
LuanSpaceship/DrawSpaceship.py
LuanSpaceship/GetInputAsFlags.py
LuanSpaceship/__init__.py
LuanSpaceship/command_line.py
luanspaceship-1.0.2.dist-info/LICENSE
luanspaceship-1.0.2.dist-info/METADATA
luanspaceship-1.0.2.dist-info/WHEEL
luanspaceship-1.0.2.dist-info/entry_points.txt
luanspaceship-1.0.2.dist-info/top_level.txt
luanspaceship-1.0.2.dist-info/RECORD
