Metadata-Version: 2.1
Name: luanspaceship
Version: 1.0.2
Summary: Prints an ASCII spaceship given an integer via flag '-length'
Author: Francisco Carrasco Varela
Author-email: ffcarrasco@uc.cl
License: UNKNOWN
Platform: UNKNOWN
Classifier: Programming Language :: Python :: 3
Classifier: License :: OSI Approved :: MIT License
Classifier: Operating System :: OS Independent
License-File: LICENSE
Requires-Dist: pyperclip
Requires-Dist: absl-py
